yaclog/__init__.py
yaclog/__main__.py
yaclog/changelog.py
yaclog/markdown.py
yaclog/version.py
yaclog/cli/__init__.py
yaclog/cli/__main__.py
yaclog/cli/cargo_toml.py
yaclog-1.6.2.dist-info/licenses/LICENSE.md
yaclog-1.6.2.dist-info/METADATA
yaclog-1.6.2.dist-info/WHEEL
yaclog-1.6.2.dist-info/entry_points.txt
yaclog-1.6.2.dist-info/top_level.txt
yaclog-1.6.2.dist-info/RECORD
