Metadata-Version: 2.4
Name: yaclog
Version: 1.6.2
Summary: Yet another changelog CLI tool.
Author-email: Andrew Cassidy <drewcassidy@me.com>
License-Expression: Apache-2.0
Project-URL: Source, https://git.offworldcolonies.nexus/drewcassidy/yaclog
Project-URL: Changelog, https://yaclog.readthedocs.io/en/stable/changelog.html
Project-URL: Docs, https://yaclog.readthedocs.io/
Keywords: changelog,commandline,markdown
Classifier: Development Status :: 5 - Production/Stable
Classifier: Intended Audience :: Developers
Classifier: Operating System :: OS Independent
Classifier: Programming Language :: Python :: 3 :: Only
Classifier: Programming Language :: Python :: 3
Classifier: Programming Language :: Python :: 3.10
Classifier: Programming Language :: Python :: 3.11
Classifier: Programming Language :: Python :: 3.12
Classifier: Programming Language :: Python :: 3.13
Classifier: Programming Language :: Python :: 3.14
Classifier: Topic :: Text Processing :: Markup :: Markdown
Classifier: Topic :: Software Development :: Version Control :: Git
Classifier: Topic :: Utilities
Requires-Python: >=3.10
License-File: LICENSE.md
Requires-Dist: Click>=8.0
Requires-Dist: GitPython>=3
Requires-Dist: packaging>=20
Requires-Dist: tomlkit>=0.11
Provides-Extra: docs
Requires-Dist: Sphinx>=8.1; extra == "docs"
Requires-Dist: sphinx-click>=2.7; extra == "docs"
Requires-Dist: sphinx-rtd-theme; extra == "docs"
Requires-Dist: myst-parser>=0.14; extra == "docs"
Requires-Dist: sphinx-gha; extra == "docs"
Requires-Dist: sphinx-copybutton; extra == "docs"
Provides-Extra: test
Requires-Dist: pytest; extra == "test"
Dynamic: license-file
